pytest_gitlab_codequality/__init__.py
pytest_gitlab_codequality/plugin.py
pytest_gitlab_codequality/recorder.py
pytest_gitlab_codequality/report.py
pytest_gitlab_codequality-0.1.1.dist-info/METADATA
pytest_gitlab_codequality-0.1.1.dist-info/WHEEL
pytest_gitlab_codequality-0.1.1.dist-info/entry_points.txt
pytest_gitlab_codequality-0.1.1.dist-info/RECORD
