Metadata-Version: 2.3
Name: pytest-gitlab-codequality
Version: 0.1.1
Summary: Collects warnings while testing and generates a GitLab Codequality Report.
Project-URL: Homepage, https://github.com/NiclasvanEyk/pytest-gitlab-codequality
Project-URL: Issues, https://github.com/NiclasvanEyk/pytest-gitlab-codequality/issues
Author-email: Niclas van Eyk <niclas.eyk@gmail.com>
Classifier: Framework :: Pytest
Requires-Python: >=3.12
Requires-Dist: pytest>=8.1.1
